sg_sesame/__init__.py
sg_sesame/_version.py
sg_sesame/ec2_utils.py
sg_sesame/py.typed
sg_sesame/sg_sesame.py
sg_sesame-0.1.1.dist-info/LICENSE
sg_sesame-0.1.1.dist-info/METADATA
sg_sesame-0.1.1.dist-info/WHEEL
sg_sesame-0.1.1.dist-info/entry_points.txt
sg_sesame-0.1.1.dist-info/top_level.txt
sg_sesame-0.1.1.dist-info/RECORD
