Metadata-Version: 2.1
Name: sg-sesame
Version: 0.1.1
Summary: Open ports in Security Groups for your current IP address
Home-page: https://github.com/stopmachine/sg-sesame
Author: Yigal Lazarev
Author-email: yigal@lazarev.co
License: Apache Software License 2.0
Keywords: sg_sesame
Platform: UNKNOWN
Classifier: Development Status :: 2 - Pre-Alpha
Classifier: License :: OSI Approved :: Apache Software License
Classifier: Natural Language :: English
Classifier: Programming Language :: Python :: 3
Requires-Python: >=3.6
Requires-Dist: requests-aws4auth (~=1.0.1)
Requires-Dist: click (~=7.1.2)
Requires-Dist: requests (~=2.25.0)
Requires-Dist: setuptools (~=50.3.2)
Requires-Dist: six (~=1.15.0)
